md2cf/__init__.py
md2cf/main.py
md2cf/utils/__init__.py
md2cf/utils/confluencemd.py
md2cf/utils/log.py
md2cf/utils/md2html.py
confluence_md-0.4.9.dist-info/METADATA
confluence_md-0.4.9.dist-info/WHEEL
confluence_md-0.4.9.dist-info/entry_points.txt
confluence_md-0.4.9.dist-info/top_level.txt
confluence_md-0.4.9.dist-info/RECORD
