Metadata-Version: 2.4
Name: confluence.md
Version: 0.4.9
Summary: Markdown to Confluence - upload any .md files to your Confluence cloud page
Home-page: https://github.com/szn/confluence.md
Download-URL: 
Author: Szymon Nieradka
License: MIT
Project-URL: Bug Tracker, https://github.com/szn/confluence.md/issues
Keywords: markdown,confluence,md,atlassian
Classifier: Programming Language :: Python :: 3
Classifier: Programming Language :: Python :: 3.7
Classifier: Programming Language :: Python :: 3.8
Classifier: Programming Language :: Python :: 3.9
Classifier: Programming Language :: Python :: 3.10
Classifier: Development Status :: 5 - Production/Stable
Classifier: Environment :: Console
Classifier: Intended Audience :: Developers
Classifier: Intended Audience :: Information Technology
Classifier: Intended Audience :: Science/Research
Classifier: Intended Audience :: System Administrators
Classifier: Natural Language :: English
Classifier: Topic :: Documentation
Classifier: Topic :: Software Development :: Documentation
Classifier: Topic :: Text Processing
Classifier: Topic :: Text Processing :: Markup :: Markdown
Classifier: Topic :: Utilities
Classifier: License :: OSI Approved :: MIT License
Classifier: Operating System :: OS Independent
Requires-Python: >=3.7
Requires-Dist: importlib; python_version == "3.7"
Requires-Dist: atlassian-python-api>=3.41.1
Requires-Dist: coloredlogs>=15.0.1
Requires-Dist: markdown2>=2.4.10
Requires-Dist: termcolor>=2.3.0
